mycalc/calculator.py
ByeongSuGo-0.0.1.dist-info/METADATA
ByeongSuGo-0.0.1.dist-info/WHEEL
ByeongSuGo-0.0.1.dist-info/top_level.txt
ByeongSuGo-0.0.1.dist-info/RECORD
