Metadata-Version: 2.1
Name: ByeongSuGo
Version: 0.0.1
Summary: oss-dev my calculator 0001
Home-page: https://github.com/eclipse1228
Download-URL: https://github.com/eclipse1228
Author: ByeongSuGo
Author-email: qudtnrh@naver.com
License: UNKNOWN
Platform: UNKNOWN
Classifier: Programming Language :: Python :: 3
